setup.py
subcommands/__init__.py
subcommands/subcommands.py
subcommands/testSubCommands.py
subcommands.egg-info/PKG-INFO
subcommands.egg-info/SOURCES.txt
subcommands.egg-info/dependency_links.txt
subcommands.egg-info/top_level.txt