Metadata-Version: 1.0
Name: subcommands
Version: 2.0
Summary: Call system commands more conveniently.
Home-page: https://github.com/zhuangchaoxi/subcommands
Author: zhuangchaoxi
Author-email: zhuangchaoxi@kaike.la
License: MIT License
Keywords: subcommands,egg
Platform: any
